<annotation>
    <filename>FireWireVsBorn of Fire_BO2_1_48.jpg</filename>
    <version>v3.0</version>
    <review_status>passed</review_status>
    <time_elapsed>212.106</time_elapsed>
    <img_label/>
    <size>
        <width>1920</width>
        <height>1080</height>
    </size>
    <padding_pxt>
        <padding_x>76</padding_x>
        <padding_y>43</padding_y>
    </padding_pxt>
    <object>
        <name>watcher</name>
        <difficulty>0</difficulty>
        <generated>0</generated>
        <is_incorrect>0</is_incorrect>
        <bndbox>
            <xmin>1795.94</xmin>
            <ymin>213.013</ymin>
            <xmax>1869.45</xmax>
            <ymax>306.8</ymax>
        </bndbox>
    </object>
    <object>
        <name>car</name>
        <difficulty>0</difficulty>
        <generated>0</generated>
        <is_incorrect>0</is_incorrect>
        <bndbox>
            <xmin>555.161</xmin>
            <ymin>628.717</ymin>
            <xmax>711.05</xmax>
            <ymax>796.013</ymax>
        </bndbox>
    </object>
    <object>
        <name>car</name>
        <difficulty>0</difficulty>
        <generated>0</generated>
        <is_incorrect>0</is_incorrect>
        <bndbox>
            <xmin>574.172</xmin>
            <ymin>788.409</ymin>
            <xmax>690.772</xmax>
            <ymax>912.613</ymax>
        </bndbox>
    </object>
    <object>
        <name>car</name>
        <difficulty>0</difficulty>
        <generated>0</generated>
        <is_incorrect>0</is_incorrect>
        <bndbox>
            <xmin>16.5196</xmin>
            <ymin>591.963</ymin>
            <xmax>130.585</xmax>
            <ymax>687.017</ymax>
        </bndbox>
    </object>
    <object>
        <name>car</name>
        <difficulty>0</difficulty>
        <generated>0</generated>
        <is_incorrect>0</is_incorrect>
        <bndbox>
            <xmin>623.6</xmin>
            <ymin>277.65</ymin>
            <xmax>717.387</xmax>
            <ymax>353.693</ymax>
        </bndbox>
    </object>
    <object>
        <name>car</name>
        <difficulty>1</difficulty>
        <generated>0</generated>
        <is_incorrect>0</is_incorrect>
        <bndbox>
            <xmin>1168.58</xmin>
            <ymin>391.715</ymin>
            <xmax>1286.45</xmax>
            <ymax>531.128</ymax>
        </bndbox>
    </object>
    <object>
        <name>car</name>
        <difficulty>0</difficulty>
        <generated>0</generated>
        <is_incorrect>0</is_incorrect>
        <bndbox>
            <xmin>1770.59</xmin>
            <ymin>621.113</ymin>
            <xmax>1929.01</xmax>
            <ymax>768.13</ymax>
        </bndbox>
    </object>
    <object>
        <name>armor</name>
        <armor_class>1</armor_class>
        <armor_color>red</armor_color>
        <generated>0</generated>
        <is_incorrect>0</is_incorrect>
        <bndbox>
            <xmin>585.578</xmin>
            <ymin>851.778</ymin>
            <xmax>609.659</xmax>
            <ymax>875.859</ymax>
        </bndbox>
    </object>
    <object>
        <name>armor</name>
        <armor_class>1</armor_class>
        <armor_color>red</armor_color>
        <generated>0</generated>
        <is_incorrect>0</is_incorrect>
        <bndbox>
            <xmin>608.391</xmin>
            <ymin>868.254</ymin>
            <xmax>657.82</xmax>
            <ymax>892.335</ymax>
        </bndbox>
    </object>
    <object>
        <name>armor</name>
        <armor_class>2</armor_class>
        <armor_color>red</armor_color>
        <generated>0</generated>
        <is_incorrect>0</is_incorrect>
        <bndbox>
            <xmin>572.904</xmin>
            <ymin>713.633</ymin>
            <xmax>599.52</xmax>
            <ymax>736.446</ymax>
        </bndbox>
    </object>
    <object>
        <name>armor</name>
        <armor_class>2</armor_class>
        <armor_color>red</armor_color>
        <generated>0</generated>
        <is_incorrect>0</is_incorrect>
        <bndbox>
            <xmin>641.343</xmin>
            <ymin>726.307</ymin>
            <xmax>671.761</xmax>
            <ymax>747.852</ymax>
        </bndbox>
    </object>
    <object>
        <name>armor</name>
        <armor_class>3</armor_class>
        <armor_color>red</armor_color>
        <generated>0</generated>
        <is_incorrect>0</is_incorrect>
        <bndbox>
            <xmin>670.493</xmin>
            <ymin>301.73</ymin>
            <xmax>699.643</xmax>
            <ymax>319.474</ymax>
        </bndbox>
    </object>
    <object>
        <name>armor</name>
        <armor_class>3</armor_class>
        <armor_color>red</armor_color>
        <generated>0</generated>
        <is_incorrect>0</is_incorrect>
        <bndbox>
            <xmin>686.97</xmin>
            <ymin>315.672</ymin>
            <xmax>705.98</xmax>
            <ymax>335.95</ymax>
        </bndbox>
    </object>
    <object>
        <name>armor</name>
        <armor_class>3</armor_class>
        <armor_color>red</armor_color>
        <generated>0</generated>
        <is_incorrect>0</is_incorrect>
        <bndbox>
            <xmin>648.948</xmin>
            <ymin>310.602</ymin>
            <xmax>670.493</xmax>
            <ymax>332.148</ymax>
        </bndbox>
    </object>
    <object>
        <name>armor</name>
        <armor_class>4</armor_class>
        <armor_color>red</armor_color>
        <generated>0</generated>
        <is_incorrect>0</is_incorrect>
        <bndbox>
            <xmin>79.8891</xmin>
            <ymin>617.311</ymin>
            <xmax>109.039</xmax>
            <ymax>636.322</ymax>
        </bndbox>
    </object>
    <object>
        <name>armor</name>
        <armor_class>4</armor_class>
        <armor_color>red</armor_color>
        <generated>0</generated>
        <is_incorrect>0</is_incorrect>
        <bndbox>
            <xmin>73.5522</xmin>
            <ymin>637.589</ymin>
            <xmax>109.039</xmax>
            <ymax>661.67</ymax>
        </bndbox>
    </object>
    <object>
        <name>armor</name>
        <armor_class>4</armor_class>
        <armor_color>red</armor_color>
        <generated>0</generated>
        <is_incorrect>0</is_incorrect>
        <bndbox>
            <xmin>25.3913</xmin>
            <ymin>646.461</ymin>
            <xmax>52.0065</xmax>
            <ymax>666.739</ymax>
        </bndbox>
    </object>
    <object>
        <name>armor</name>
        <armor_class>1</armor_class>
        <armor_color>blue</armor_color>
        <generated>0</generated>
        <is_incorrect>0</is_incorrect>
        <bndbox>
            <xmin>1807.34</xmin>
            <ymin>697.157</ymin>
            <xmax>1837.76</xmax>
            <ymax>722.504</ymax>
        </bndbox>
    </object>
    <object>
        <name>armor</name>
        <armor_class>1</armor_class>
        <armor_color>blue</armor_color>
        <generated>0</generated>
        <is_incorrect>0</is_incorrect>
        <bndbox>
            <xmin>1850.43</xmin>
            <ymin>725.039</ymin>
            <xmax>1896.06</xmax>
            <ymax>749.12</ymax>
        </bndbox>
    </object>
    <object>
        <name>armor</name>
        <armor_class>1</armor_class>
        <armor_color>blue</armor_color>
        <generated>0</generated>
        <is_incorrect>0</is_incorrect>
        <bndbox>
            <xmin>1790.87</xmin>
            <ymin>713.633</ymin>
            <xmax>1825.09</xmax>
            <ymax>742.783</ymax>
        </bndbox>
    </object>
    <object>
        <name>armor</name>
        <armor_class>2</armor_class>
        <armor_color>blue</armor_color>
        <generated>0</generated>
        <is_incorrect>0</is_incorrect>
        <bndbox>
            <xmin>1238.28</xmin>
            <ymin>495.641</ymin>
            <xmax>1264.9</xmax>
            <ymax>517.187</ymax>
        </bndbox>
    </object>
    <object>
        <name>armor</name>
        <armor_class>7</armor_class>
        <armor_color>blue</armor_color>
        <generated>0</generated>
        <is_incorrect>0</is_incorrect>
        <bndbox>
            <xmin>1814.95</xmin>
            <ymin>263.709</ymin>
            <xmax>1859.31</xmax>
            <ymax>281.452</ymax>
        </bndbox>
    </object>
</annotation>
