<annotation>
    <filename>DianChuangVsRPS_BO2_2_101.jpg</filename>
    <version>v3.0</version>
    <review_status>passed</review_status>
    <time_elapsed>696</time_elapsed>
    <img_label/>
    <size>
        <width>1920</width>
        <height>1080</height>
    </size>
    <padding_pxt>
        <padding_x>76</padding_x>
        <padding_y>43</padding_y>
    </padding_pxt>
    <object>
        <name>armor</name>
        <armor_class>6</armor_class>
        <armor_color>red</armor_color>
        <generated>0</generated>
        <is_incorrect>0</is_incorrect>
        <bndbox>
            <xmin>177.478</xmin>
            <ymin>703.493</ymin>
            <xmax>207.896</xmax>
            <ymax>765.596</ymax>
        </bndbox>
    </object>
    <object>
        <name>armor</name>
        <armor_class>6</armor_class>
        <armor_color>red</armor_color>
        <generated>0</generated>
        <is_incorrect>0</is_incorrect>
        <bndbox>
            <xmin>143.259</xmin>
            <ymin>713.633</ymin>
            <xmax>154.665</xmax>
            <ymax>759.259</ymax>
        </bndbox>
    </object>
    <object>
        <name>armor</name>
        <armor_class>6</armor_class>
        <armor_color>red</armor_color>
        <generated>0</generated>
        <is_incorrect>0</is_incorrect>
        <bndbox>
            <xmin>91.2957</xmin>
            <ymin>716.167</ymin>
            <xmax>114.109</xmax>
            <ymax>784.607</ymax>
        </bndbox>
    </object>
    <object>
        <name>ignore</name>
        <generated>0</generated>
        <is_incorrect>0</is_incorrect>
        <bndbox>
            <xmin>124.248</xmin>
            <ymin>698.424</ymin>
            <xmax>168.607</xmax>
            <ymax>713.633</ymax>
        </bndbox>
    </object>
    <object>
        <name>ignore</name>
        <generated>0</generated>
        <is_incorrect>0</is_incorrect>
        <bndbox>
            <xmin>107.772</xmin>
            <ymin>693.354</ymin>
            <xmax>130.585</xmax>
            <ymax>709.83</ymax>
        </bndbox>
    </object>
    <object>
        <name>armor</name>
        <armor_class>2</armor_class>
        <armor_color>red</armor_color>
        <generated>0</generated>
        <is_incorrect>0</is_incorrect>
        <bndbox>
            <xmin>282.672</xmin>
            <ymin>770.665</ymin>
            <xmax>306.752</xmax>
            <ymax>789.676</ymax>
        </bndbox>
    </object>
    <object>
        <name>armor</name>
        <armor_class>2</armor_class>
        <armor_color>red</armor_color>
        <generated>0</generated>
        <is_incorrect>0</is_incorrect>
        <bndbox>
            <xmin>221.837</xmin>
            <ymin>771.933</ymin>
            <xmax>245.917</xmax>
            <ymax>790.943</ymax>
        </bndbox>
    </object>
    <object>
        <name>armor</name>
        <armor_class>2</armor_class>
        <armor_color>blue</armor_color>
        <generated>0</generated>
        <is_incorrect>0</is_incorrect>
        <bndbox>
            <xmin>1567.81</xmin>
            <ymin>788.409</ymin>
            <xmax>1593.15</xmax>
            <ymax>807.42</ymax>
        </bndbox>
    </object>
    <object>
        <name>armor</name>
        <armor_class>2</armor_class>
        <armor_color>blue</armor_color>
        <generated>0</generated>
        <is_incorrect>0</is_incorrect>
        <bndbox>
            <xmin>1505.7</xmin>
            <ymin>783.339</ymin>
            <xmax>1524.72</xmax>
            <ymax>802.35</ymax>
        </bndbox>
    </object>
    <object>
        <name>armor</name>
        <armor_class>3</armor_class>
        <armor_color>blue</armor_color>
        <generated>0</generated>
        <is_incorrect>0</is_incorrect>
        <bndbox>
            <xmin>1027.9</xmin>
            <ymin>704.761</ymin>
            <xmax>1046.91</xmax>
            <ymax>722.504</ymax>
        </bndbox>
    </object>
    <object>
        <name>armor</name>
        <armor_class>3</armor_class>
        <armor_color>blue</armor_color>
        <generated>0</generated>
        <is_incorrect>0</is_incorrect>
        <bndbox>
            <xmin>986.074</xmin>
            <ymin>695.889</ymin>
            <xmax>1017.76</xmax>
            <ymax>712.365</ymax>
        </bndbox>
    </object>
    <object>
        <name>armor</name>
        <armor_class>3</armor_class>
        <armor_color>blue</armor_color>
        <generated>0</generated>
        <is_incorrect>0</is_incorrect>
        <bndbox>
            <xmin>982.272</xmin>
            <ymin>712.365</ymin>
            <xmax>1005.08</xmax>
            <ymax>731.376</ymax>
        </bndbox>
    </object>
    <object>
        <name>car</name>
        <difficulty>0</difficulty>
        <generated>0</generated>
        <is_incorrect>0</is_incorrect>
        <bndbox>
            <xmin>1486.69</xmin>
            <ymin>679.413</ymin>
            <xmax>1628.64</xmax>
            <ymax>831.5</ymax>
        </bndbox>
    </object>
    <object>
        <name>car</name>
        <difficulty>0</difficulty>
        <generated>0</generated>
        <is_incorrect>0</is_incorrect>
        <bndbox>
            <xmin>965.796</xmin>
            <ymin>665.472</ymin>
            <xmax>1069.72</xmax>
            <ymax>744.05</ymax>
        </bndbox>
    </object>
    <object>
        <name>car</name>
        <difficulty>0</difficulty>
        <generated>0</generated>
        <is_incorrect>0</is_incorrect>
        <bndbox>
            <xmin>199.024</xmin>
            <ymin>665.472</ymin>
            <xmax>339.704</xmax>
            <ymax>802.35</ymax>
        </bndbox>
    </object>
    <object>
        <name>base</name>
        <difficulty>0</difficulty>
        <generated>0</generated>
        <is_incorrect>0</is_incorrect>
        <bndbox>
            <xmin>64.6804</xmin>
            <ymin>683.215</ymin>
            <xmax>245.917</xmax>
            <ymax>851.778</ymax>
        </bndbox>
    </object>
    <object>
        <name>armor</name>
        <armor_class>7</armor_class>
        <armor_color>red</armor_color>
        <generated>0</generated>
        <is_incorrect>0</is_incorrect>
        <bndbox>
            <xmin>656.552</xmin>
            <ymin>719.97</ymin>
            <xmax>695.841</xmax>
            <ymax>735.178</ymax>
        </bndbox>
    </object>
    <object>
        <name>armor</name>
        <armor_class>1</armor_class>
        <armor_color>red</armor_color>
        <generated>0</generated>
        <is_incorrect>0</is_incorrect>
        <bndbox>
            <xmin>411.946</xmin>
            <ymin>542.535</ymin>
            <xmax>447.433</xmax>
            <ymax>557.743</ymax>
        </bndbox>
    </object>
    <object>
        <name>armor</name>
        <armor_class>4</armor_class>
        <armor_color>red</armor_color>
        <generated>0</generated>
        <is_incorrect>0</is_incorrect>
        <bndbox>
            <xmin>358.715</xmin>
            <ymin>728.841</ymin>
            <xmax>399.272</xmax>
            <ymax>742.783</ymax>
        </bndbox>
    </object>
    <object>
        <name>armor</name>
        <armor_class>4</armor_class>
        <armor_color>red</armor_color>
        <generated>0</generated>
        <is_incorrect>0</is_incorrect>
        <bndbox>
            <xmin>367.587</xmin>
            <ymin>747.852</ymin>
            <xmax>396.737</xmax>
            <ymax>761.793</ymax>
        </bndbox>
    </object>
    <object>
        <name>armor</name>
        <armor_class>4</armor_class>
        <armor_color>red</armor_color>
        <generated>0</generated>
        <is_incorrect>0</is_incorrect>
        <bndbox>
            <xmin>340.972</xmin>
            <ymin>736.446</ymin>
            <xmax>354.913</xmax>
            <ymax>754.189</ymax>
        </bndbox>
    </object>
    <object>
        <name>armor</name>
        <armor_class>3</armor_class>
        <armor_color>red</armor_color>
        <generated>0</generated>
        <is_incorrect>0</is_incorrect>
        <bndbox>
            <xmin>556.428</xmin>
            <ymin>448.748</ymin>
            <xmax>589.38</xmax>
            <ymax>462.689</ymax>
        </bndbox>
    </object>
    <object>
        <name>armor</name>
        <armor_class>3</armor_class>
        <armor_color>red</armor_color>
        <generated>0</generated>
        <is_incorrect>0</is_incorrect>
        <bndbox>
            <xmin>567.835</xmin>
            <ymin>462.689</ymin>
            <xmax>593.183</xmax>
            <ymax>479.165</ymax>
        </bndbox>
    </object>
    <object>
        <name>armor</name>
        <armor_class>3</armor_class>
        <armor_color>red</armor_color>
        <generated>0</generated>
        <is_incorrect>0</is_incorrect>
        <bndbox>
            <xmin>533.615</xmin>
            <ymin>460.154</ymin>
            <xmax>553.893</xmax>
            <ymax>476.63</ymax>
        </bndbox>
    </object>
    <object>
        <name>armor</name>
        <armor_class>1</armor_class>
        <armor_color>blue</armor_color>
        <generated>0</generated>
        <is_incorrect>0</is_incorrect>
        <bndbox>
            <xmin>920.17</xmin>
            <ymin>604.637</ymin>
            <xmax>949.32</xmax>
            <ymax>622.38</ymax>
        </bndbox>
    </object>
    <object>
        <name>armor</name>
        <armor_class>1</armor_class>
        <armor_color>blue</armor_color>
        <generated>0</generated>
        <is_incorrect>0</is_incorrect>
        <bndbox>
            <xmin>868.207</xmin>
            <ymin>604.637</ymin>
            <xmax>896.089</xmax>
            <ymax>624.915</ymax>
        </bndbox>
    </object>
    <object>
        <name>armor</name>
        <armor_class>4</armor_class>
        <armor_color>blue</armor_color>
        <generated>0</generated>
        <is_incorrect>0</is_incorrect>
        <bndbox>
            <xmin>832.72</xmin>
            <ymin>626.183</ymin>
            <xmax>852.998</xmax>
            <ymax>637.589</ymax>
        </bndbox>
    </object>
    <object>
        <name>armor</name>
        <armor_class>4</armor_class>
        <armor_color>blue</armor_color>
        <generated>0</generated>
        <is_incorrect>0</is_incorrect>
        <bndbox>
            <xmin>826.383</xmin>
            <ymin>646.461</ymin>
            <xmax>849.196</xmax>
            <ymax>661.67</ymax>
        </bndbox>
    </object>
    <object>
        <name>armor</name>
        <armor_class>4</armor_class>
        <armor_color>blue</armor_color>
        <generated>0</generated>
        <is_incorrect>0</is_incorrect>
        <bndbox>
            <xmin>784.559</xmin>
            <ymin>645.193</ymin>
            <xmax>802.302</xmax>
            <ymax>665.472</ymax>
        </bndbox>
    </object>
    <object>
        <name>watcher</name>
        <difficulty>0</difficulty>
        <generated>0</generated>
        <is_incorrect>0</is_incorrect>
        <bndbox>
            <xmin>647.68</xmin>
            <ymin>687.017</ymin>
            <xmax>707.248</xmax>
            <ymax>757.991</ymax>
        </bndbox>
    </object>
    <object>
        <name>car</name>
        <difficulty>0</difficulty>
        <generated>0</generated>
        <is_incorrect>0</is_incorrect>
        <bndbox>
            <xmin>385.33</xmin>
            <ymin>462.689</ymin>
            <xmax>475.315</xmax>
            <ymax>575.487</ymax>
        </bndbox>
    </object>
    <object>
        <name>car</name>
        <difficulty>0</difficulty>
        <generated>0</generated>
        <is_incorrect>0</is_incorrect>
        <bndbox>
            <xmin>333.367</xmin>
            <ymin>690.82</ymin>
            <xmax>417.015</xmax>
            <ymax>775.735</ymax>
        </bndbox>
    </object>
    <object>
        <name>car</name>
        <difficulty>0</difficulty>
        <generated>0</generated>
        <is_incorrect>0</is_incorrect>
        <bndbox>
            <xmin>519.674</xmin>
            <ymin>424.667</ymin>
            <xmax>599.52</xmax>
            <ymax>485.502</ymax>
        </bndbox>
    </object>
    <object>
        <name>car</name>
        <difficulty>0</difficulty>
        <generated>0</generated>
        <is_incorrect>0</is_incorrect>
        <bndbox>
            <xmin>770.617</xmin>
            <ymin>603.37</ymin>
            <xmax>872.009</xmax>
            <ymax>685.75</ymax>
        </bndbox>
    </object>
    <object>
        <name>car</name>
        <difficulty>0</difficulty>
        <generated>0</generated>
        <is_incorrect>0</is_incorrect>
        <bndbox>
            <xmin>846.661</xmin>
            <ymin>543.802</ymin>
            <xmax>970.865</xmax>
            <ymax>654.065</ymax>
        </bndbox>
    </object>
</annotation>
