<annotation>
    <filename>LingzhiTechAresVsThunder_BO2_2_352.jpg</filename>
    <version>v3.0</version>
    <review_status>passed</review_status>
    <time_elapsed>231</time_elapsed>
    <img_label/>
    <size>
        <width>1920</width>
        <height>1080</height>
    </size>
    <padding_pxt>
        <padding_x>76</padding_x>
        <padding_y>43</padding_y>
    </padding_pxt>
    <object>
        <name>armor</name>
        <armor_class>8</armor_class>
        <armor_color>blue</armor_color>
        <generated>0</generated>
        <is_incorrect>0</is_incorrect>
        <bndbox>
            <xmin>1158.44</xmin>
            <ymin>230.757</ymin>
            <xmax>1191.39</xmax>
            <ymax>247.233</ymax>
        </bndbox>
    </object>
    <object>
        <name>armor</name>
        <armor_class>6</armor_class>
        <armor_color>blue</armor_color>
        <generated>0</generated>
        <is_incorrect>0</is_incorrect>
        <bndbox>
            <xmin>1231.95</xmin>
            <ymin>282.72</ymin>
            <xmax>1243.35</xmax>
            <ymax>335.95</ymax>
        </bndbox>
    </object>
    <object>
        <name>armor</name>
        <armor_class>6</armor_class>
        <armor_color>blue</armor_color>
        <generated>0</generated>
        <is_incorrect>0</is_incorrect>
        <bndbox>
            <xmin>1190.12</xmin>
            <ymin>256.104</ymin>
            <xmax>1206.6</xmax>
            <ymax>295.393</ymax>
        </bndbox>
    </object>
    <object>
        <name>armor</name>
        <armor_class>6</armor_class>
        <armor_color>blue</armor_color>
        <generated>0</generated>
        <is_incorrect>0</is_incorrect>
        <bndbox>
            <xmin>1167.31</xmin>
            <ymin>245.965</ymin>
            <xmax>1187.59</xmax>
            <ymax>291.591</ymax>
        </bndbox>
    </object>
    <object>
        <name>armor</name>
        <armor_class>6</armor_class>
        <armor_color>blue</armor_color>
        <generated>0</generated>
        <is_incorrect>0</is_incorrect>
        <bndbox>
            <xmin>1093.8</xmin>
            <ymin>273.848</ymin>
            <xmax>1106.48</xmax>
            <ymax>327.078</ymax>
        </bndbox>
    </object>
    <object>
        <name>armor</name>
        <armor_class>8</armor_class>
        <armor_color>blue</armor_color>
        <generated>0</generated>
        <is_incorrect>0</is_incorrect>
        <bndbox>
            <xmin>1152.1</xmin>
            <ymin>292.859</ymin>
            <xmax>1186.32</xmax>
            <ymax>309.335</ymax>
        </bndbox>
    </object>
    <object>
        <name>base</name>
        <difficulty>0</difficulty>
        <generated>0</generated>
        <is_incorrect>0</is_incorrect>
        <bndbox>
            <xmin>1090</xmin>
            <ymin>224.42</ymin>
            <xmax>1245.89</xmax>
            <ymax>347.357</ymax>
        </bndbox>
    </object>
    <object>
        <name>armor</name>
        <armor_class>7</armor_class>
        <armor_color>grey</armor_color>
        <generated>0</generated>
        <is_incorrect>0</is_incorrect>
        <bndbox>
            <xmin>884.683</xmin>
            <ymin>320.741</ymin>
            <xmax>915.1</xmax>
            <ymax>334.683</ymax>
        </bndbox>
    </object>
    <object>
        <name>watcher</name>
        <difficulty>0</difficulty>
        <generated>0</generated>
        <is_incorrect>0</is_incorrect>
        <bndbox>
            <xmin>872.009</xmin>
            <ymin>286.522</ymin>
            <xmax>918.902</xmax>
            <ymax>334.683</ymax>
        </bndbox>
    </object>
    <object>
        <name>armor</name>
        <armor_class>1</armor_class>
        <armor_color>red</armor_color>
        <generated>0</generated>
        <is_incorrect>0</is_incorrect>
        <bndbox>
            <xmin>278.87</xmin>
            <ymin>503.246</ymin>
            <xmax>300.415</xmax>
            <ymax>518.454</ymax>
        </bndbox>
    </object>
    <object>
        <name>armor</name>
        <armor_class>1</armor_class>
        <armor_color>red</armor_color>
        <generated>0</generated>
        <is_incorrect>0</is_incorrect>
        <bndbox>
            <xmin>250.987</xmin>
            <ymin>524.791</ymin>
            <xmax>289.009</xmax>
            <ymax>542.535</ymax>
        </bndbox>
    </object>
    <object>
        <name>armor</name>
        <armor_class>1</armor_class>
        <armor_color>red</armor_color>
        <generated>0</generated>
        <is_incorrect>0</is_incorrect>
        <bndbox>
            <xmin>220.57</xmin>
            <ymin>518.454</ymin>
            <xmax>237.046</xmax>
            <ymax>540</ymax>
        </bndbox>
    </object>
    <object>
        <name>armor</name>
        <armor_class>1</armor_class>
        <armor_color>blue</armor_color>
        <generated>0</generated>
        <is_incorrect>0</is_incorrect>
        <bndbox>
            <xmin>1267.43</xmin>
            <ymin>654.065</ymin>
            <xmax>1307.99</xmax>
            <ymax>673.076</ymax>
        </bndbox>
    </object>
    <object>
        <name>armor</name>
        <armor_class>1</armor_class>
        <armor_color>blue</armor_color>
        <generated>0</generated>
        <is_incorrect>0</is_incorrect>
        <bndbox>
            <xmin>1239.55</xmin>
            <ymin>629.985</ymin>
            <xmax>1262.37</xmax>
            <ymax>650.263</ymax>
        </bndbox>
    </object>
    <object>
        <name>armor</name>
        <armor_class>1</armor_class>
        <armor_color>blue</armor_color>
        <generated>0</generated>
        <is_incorrect>0</is_incorrect>
        <bndbox>
            <xmin>1225.61</xmin>
            <ymin>641.391</ymin>
            <xmax>1244.62</xmax>
            <ymax>665.472</ymax>
        </bndbox>
    </object>
    <object>
        <name>armor</name>
        <armor_class>3</armor_class>
        <armor_color>grey</armor_color>
        <generated>0</generated>
        <is_incorrect>0</is_incorrect>
        <bndbox>
            <xmin>271.265</xmin>
            <ymin>660.402</ymin>
            <xmax>305.485</xmax>
            <ymax>676.878</ymax>
        </bndbox>
    </object>
    <object>
        <name>armor</name>
        <armor_class>3</armor_class>
        <armor_color>grey</armor_color>
        <generated>0</generated>
        <is_incorrect>0</is_incorrect>
        <bndbox>
            <xmin>318.159</xmin>
            <ymin>674.343</ymin>
            <xmax>338.437</xmax>
            <ymax>692.087</ymax>
        </bndbox>
    </object>
    <object>
        <name>armor</name>
        <armor_class>3</armor_class>
        <armor_color>grey</armor_color>
        <generated>0</generated>
        <is_incorrect>0</is_incorrect>
        <bndbox>
            <xmin>264.928</xmin>
            <ymin>676.878</ymin>
            <xmax>290.276</xmax>
            <ymax>697.157</ymax>
        </bndbox>
    </object>
    <object>
        <name>armor</name>
        <armor_class>2</armor_class>
        <armor_color>blue</armor_color>
        <generated>0</generated>
        <is_incorrect>0</is_incorrect>
        <bndbox>
            <xmin>17.787</xmin>
            <ymin>1021.61</ymin>
            <xmax>52.0065</xmax>
            <ymax>1041.89</ymax>
        </bndbox>
    </object>
    <object>
        <name>armor</name>
        <armor_class>4</armor_class>
        <armor_color>blue</armor_color>
        <generated>0</generated>
        <is_incorrect>0</is_incorrect>
        <bndbox>
            <xmin>1512.04</xmin>
            <ymin>697.157</ymin>
            <xmax>1527.25</xmax>
            <ymax>717.435</ymax>
        </bndbox>
    </object>
    <object>
        <name>armor</name>
        <armor_class>4</armor_class>
        <armor_color>blue</armor_color>
        <generated>0</generated>
        <is_incorrect>0</is_incorrect>
        <bndbox>
            <xmin>1457.54</xmin>
            <ymin>681.948</ymin>
            <xmax>1475.29</xmax>
            <ymax>699.691</ymax>
        </bndbox>
    </object>
    <object>
        <name>armor</name>
        <armor_class>4</armor_class>
        <armor_color>blue</armor_color>
        <generated>0</generated>
        <is_incorrect>0</is_incorrect>
        <bndbox>
            <xmin>1466.42</xmin>
            <ymin>708.563</ymin>
            <xmax>1496.83</xmax>
            <ymax>727.574</ymax>
        </bndbox>
    </object>
    <object>
        <name>armor</name>
        <armor_class>4</armor_class>
        <armor_color>red</armor_color>
        <generated>0</generated>
        <is_incorrect>0</is_incorrect>
        <bndbox>
            <xmin>964.528</xmin>
            <ymin>287.789</ymin>
            <xmax>983.539</xmax>
            <ymax>300.463</ymax>
        </bndbox>
    </object>
    <object>
        <name>car</name>
        <difficulty>1</difficulty>
        <generated>0</generated>
        <is_incorrect>0</is_incorrect>
        <bndbox>
            <xmin>-26.5717</xmin>
            <ymin>924.02</ymin>
            <xmax>110.307</xmax>
            <ymax>1064.7</ymax>
        </bndbox>
    </object>
    <object>
        <name>car</name>
        <difficulty>1</difficulty>
        <generated>0</generated>
        <is_incorrect>0</is_incorrect>
        <bndbox>
            <xmin>925.239</xmin>
            <ymin>264.976</ymin>
            <xmax>1001.28</xmax>
            <ymax>329.613</ymax>
        </bndbox>
    </object>
    <object>
        <name>car</name>
        <difficulty>0</difficulty>
        <generated>0</generated>
        <is_incorrect>0</is_incorrect>
        <bndbox>
            <xmin>1438.53</xmin>
            <ymin>659.135</ymin>
            <xmax>1534.85</xmax>
            <ymax>741.515</ymax>
        </bndbox>
    </object>
    <object>
        <name>car</name>
        <difficulty>0</difficulty>
        <generated>0</generated>
        <is_incorrect>0</is_incorrect>
        <bndbox>
            <xmin>247.185</xmin>
            <ymin>627.45</ymin>
            <xmax>356.18</xmax>
            <ymax>713.633</ymax>
        </bndbox>
    </object>
    <object>
        <name>car</name>
        <difficulty>0</difficulty>
        <generated>0</generated>
        <is_incorrect>0</is_incorrect>
        <bndbox>
            <xmin>215.5</xmin>
            <ymin>444.946</ymin>
            <xmax>315.624</xmax>
            <ymax>557.743</ymax>
        </bndbox>
    </object>
    <object>
        <name>car</name>
        <difficulty>0</difficulty>
        <generated>0</generated>
        <is_incorrect>0</is_incorrect>
        <bndbox>
            <xmin>1219.27</xmin>
            <ymin>586.893</ymin>
            <xmax>1325.73</xmax>
            <ymax>688.285</ymax>
        </bndbox>
    </object>
</annotation>
