<annotation>
    <filename>WMJVsWolfTooth_BO2_2_58.jpg</filename>
    <version>v3.0</version>
    <review_status>passed</review_status>
    <time_elapsed>4053</time_elapsed>
    <img_label/>
    <size>
        <width>1920</width>
        <height>1080</height>
    </size>
    <padding_pxt>
        <padding_x>76</padding_x>
        <padding_y>43</padding_y>
    </padding_pxt>
    <object>
        <name>armor</name>
        <armor_class>3</armor_class>
        <armor_color>red</armor_color>
        <generated>0</generated>
        <is_incorrect>0</is_incorrect>
        <bndbox>
            <xmin>411.946</xmin>
            <ymin>915.148</ymin>
            <xmax>430.957</xmax>
            <ymax>935.426</ymax>
        </bndbox>
    </object>
    <object>
        <name>armor</name>
        <armor_class>2</armor_class>
        <armor_color>red</armor_color>
        <generated>0</generated>
        <is_incorrect>0</is_incorrect>
        <bndbox>
            <xmin>671.761</xmin>
            <ymin>861.917</ymin>
            <xmax>699.643</xmax>
            <ymax>879.661</ymax>
        </bndbox>
    </object>
    <object>
        <name>armor</name>
        <armor_class>7</armor_class>
        <armor_color>blue</armor_color>
        <generated>0</generated>
        <is_incorrect>0</is_incorrect>
        <bndbox>
            <xmin>1168.58</xmin>
            <ymin>308.067</ymin>
            <xmax>1205.33</xmax>
            <ymax>323.276</ymax>
        </bndbox>
    </object>
    <object>
        <name>watcher</name>
        <difficulty>0</difficulty>
        <generated>0</generated>
        <is_incorrect>0</is_incorrect>
        <bndbox>
            <xmin>1155.9</xmin>
            <ymin>280.185</ymin>
            <xmax>1206.6</xmax>
            <ymax>346.089</ymax>
        </bndbox>
    </object>
    <object>
        <name>ignore</name>
        <generated>0</generated>
        <is_incorrect>0</is_incorrect>
        <bndbox>
            <xmin>1596.96</xmin>
            <ymin>214.28</ymin>
            <xmax>1632.44</xmax>
            <ymax>229.489</ymax>
        </bndbox>
    </object>
    <object>
        <name>armor</name>
        <armor_class>6</armor_class>
        <armor_color>blue</armor_color>
        <generated>0</generated>
        <is_incorrect>0</is_incorrect>
        <bndbox>
            <xmin>1566.54</xmin>
            <ymin>221.885</ymin>
            <xmax>1593.15</xmax>
            <ymax>275.115</ymax>
        </bndbox>
    </object>
    <object>
        <name>armor</name>
        <armor_class>6</armor_class>
        <armor_color>blue</armor_color>
        <generated>0</generated>
        <is_incorrect>0</is_incorrect>
        <bndbox>
            <xmin>1608.36</xmin>
            <ymin>225.687</ymin>
            <xmax>1619.77</xmax>
            <ymax>254.837</ymax>
        </bndbox>
    </object>
    <object>
        <name>armor</name>
        <armor_class>6</armor_class>
        <armor_color>blue</armor_color>
        <generated>0</generated>
        <is_incorrect>0</is_incorrect>
        <bndbox>
            <xmin>1634.98</xmin>
            <ymin>225.687</ymin>
            <xmax>1655.26</xmax>
            <ymax>281.452</ymax>
        </bndbox>
    </object>
    <object>
        <name>base</name>
        <difficulty>0</difficulty>
        <generated>0</generated>
        <is_incorrect>0</is_incorrect>
        <bndbox>
            <xmin>1537.39</xmin>
            <ymin>205.409</ymin>
            <xmax>1674.27</xmax>
            <ymax>332.148</ymax>
        </bndbox>
    </object>
    <object>
        <name>armor</name>
        <armor_class>2</armor_class>
        <armor_color>blue</armor_color>
        <generated>0</generated>
        <is_incorrect>0</is_incorrect>
        <bndbox>
            <xmin>764.28</xmin>
            <ymin>467.759</ymin>
            <xmax>792.163</xmax>
            <ymax>486.77</ymax>
        </bndbox>
    </object>
    <object>
        <name>armor</name>
        <armor_class>3</armor_class>
        <armor_color>blue</armor_color>
        <generated>0</generated>
        <is_incorrect>0</is_incorrect>
        <bndbox>
            <xmin>917.635</xmin>
            <ymin>566.615</ymin>
            <xmax>935.378</xmax>
            <ymax>585.626</ymax>
        </bndbox>
    </object>
    <object>
        <name>armor</name>
        <armor_class>3</armor_class>
        <armor_color>blue</armor_color>
        <generated>0</generated>
        <is_incorrect>0</is_incorrect>
        <bndbox>
            <xmin>868.207</xmin>
            <ymin>551.407</ymin>
            <xmax>889.752</xmax>
            <ymax>566.615</ymax>
        </bndbox>
    </object>
    <object>
        <name>armor</name>
        <armor_class>3</armor_class>
        <armor_color>blue</armor_color>
        <generated>0</generated>
        <is_incorrect>0</is_incorrect>
        <bndbox>
            <xmin>875.811</xmin>
            <ymin>567.883</ymin>
            <xmax>901.159</xmax>
            <ymax>585.626</ymax>
        </bndbox>
    </object>
    <object>
        <name>armor</name>
        <armor_class>4</armor_class>
        <armor_color>blue</armor_color>
        <generated>0</generated>
        <is_incorrect>0</is_incorrect>
        <bndbox>
            <xmin>1157.17</xmin>
            <ymin>490.572</ymin>
            <xmax>1173.65</xmax>
            <ymax>510.85</ymax>
        </bndbox>
    </object>
    <object>
        <name>armor</name>
        <armor_class>4</armor_class>
        <armor_color>blue</armor_color>
        <generated>0</generated>
        <is_incorrect>0</is_incorrect>
        <bndbox>
            <xmin>1117.88</xmin>
            <ymin>503.246</ymin>
            <xmax>1144.5</xmax>
            <ymax>523.524</ymax>
        </bndbox>
    </object>
    <object>
        <name>car</name>
        <difficulty>2</difficulty>
        <generated>0</generated>
        <is_incorrect>0</is_incorrect>
        <bndbox>
            <xmin>333.367</xmin>
            <ymin>863.185</ymin>
            <xmax>439.828</xmax>
            <ymax>950.635</ymax>
        </bndbox>
    </object>
    <object>
        <name>car</name>
        <difficulty>2</difficulty>
        <generated>0</generated>
        <is_incorrect>0</is_incorrect>
        <bndbox>
            <xmin>1268.7</xmin>
            <ymin>428.47</ymin>
            <xmax>1367.56</xmax>
            <ymax>531.128</ymax>
        </bndbox>
    </object>
    <object>
        <name>car</name>
        <difficulty>0</difficulty>
        <generated>0</generated>
        <is_incorrect>0</is_incorrect>
        <bndbox>
            <xmin>1102.67</xmin>
            <ymin>460.154</ymin>
            <xmax>1186.32</xmax>
            <ymax>529.861</ymax>
        </bndbox>
    </object>
    <object>
        <name>car</name>
        <difficulty>0</difficulty>
        <generated>0</generated>
        <is_incorrect>0</is_incorrect>
        <bndbox>
            <xmin>856.8</xmin>
            <ymin>529.861</ymin>
            <xmax>941.715</xmax>
            <ymax>605.904</ymax>
        </bndbox>
    </object>
    <object>
        <name>car</name>
        <difficulty>0</difficulty>
        <generated>0</generated>
        <is_incorrect>0</is_incorrect>
        <bndbox>
            <xmin>730.061</xmin>
            <ymin>390.448</ymin>
            <xmax>828.917</xmax>
            <ymax>505.78</ymax>
        </bndbox>
    </object>
    <object>
        <name>car</name>
        <difficulty>0</difficulty>
        <generated>0</generated>
        <is_incorrect>0</is_incorrect>
        <bndbox>
            <xmin>623.6</xmin>
            <ymin>752.922</ymin>
            <xmax>747.804</xmax>
            <ymax>896.137</ymax>
        </bndbox>
    </object>
</annotation>
