<annotation>
    <filename>FireWireVsBorn of Fire_BO2_1_283.jpg</filename>
    <version>v3.0</version>
    <review_status>passed</review_status>
    <time_elapsed>3819.09</time_elapsed>
    <img_label/>
    <size>
        <width>1920</width>
        <height>1080</height>
    </size>
    <padding_pxt>
        <padding_x>76</padding_x>
        <padding_y>43</padding_y>
    </padding_pxt>
    <object>
        <name>armor</name>
        <armor_class>8</armor_class>
        <armor_color>blue</armor_color>
        <generated>0</generated>
        <is_incorrect>0</is_incorrect>
        <bndbox>
            <xmin>1434.73</xmin>
            <ymin>305.533</ymin>
            <xmax>1453.74</xmax>
            <ymax>320.741</ymax>
        </bndbox>
    </object>
    <object>
        <name>armor</name>
        <armor_class>8</armor_class>
        <armor_color>blue</armor_color>
        <generated>0</generated>
        <is_incorrect>0</is_incorrect>
        <bndbox>
            <xmin>1409.38</xmin>
            <ymin>308.067</ymin>
            <xmax>1444.87</xmax>
            <ymax>324.543</ymax>
        </bndbox>
    </object>
    <object>
        <name>armor</name>
        <armor_class>8</armor_class>
        <armor_color>blue</armor_color>
        <generated>0</generated>
        <is_incorrect>0</is_incorrect>
        <bndbox>
            <xmin>1405.58</xmin>
            <ymin>372.704</ymin>
            <xmax>1441.07</xmax>
            <ymax>390.448</ymax>
        </bndbox>
    </object>
    <object>
        <name>armor</name>
        <armor_class>6</armor_class>
        <armor_color>blue</armor_color>
        <generated>0</generated>
        <is_incorrect>0</is_incorrect>
        <bndbox>
            <xmin>1419.52</xmin>
            <ymin>325.811</ymin>
            <xmax>1441.07</xmax>
            <ymax>372.704</ymax>
        </bndbox>
    </object>
    <object>
        <name>armor</name>
        <armor_class>6</armor_class>
        <armor_color>blue</armor_color>
        <generated>0</generated>
        <is_incorrect>0</is_incorrect>
        <bndbox>
            <xmin>1443.6</xmin>
            <ymin>328.346</ymin>
            <xmax>1458.81</xmax>
            <ymax>372.704</ymax>
        </bndbox>
    </object>
    <object>
        <name>armor</name>
        <armor_class>6</armor_class>
        <armor_color>blue</armor_color>
        <generated>0</generated>
        <is_incorrect>0</is_incorrect>
        <bndbox>
            <xmin>1481.62</xmin>
            <ymin>365.1</ymin>
            <xmax>1504.44</xmax>
            <ymax>415.796</ymax>
        </bndbox>
    </object>
    <object>
        <name>armor</name>
        <armor_class>6</armor_class>
        <armor_color>blue</armor_color>
        <generated>0</generated>
        <is_incorrect>0</is_incorrect>
        <bndbox>
            <xmin>1340.94</xmin>
            <ymin>353.693</ymin>
            <xmax>1358.69</xmax>
            <ymax>405.657</ymax>
        </bndbox>
    </object>
    <object>
        <name>base</name>
        <difficulty>0</difficulty>
        <generated>0</generated>
        <is_incorrect>0</is_incorrect>
        <bndbox>
            <xmin>1335.87</xmin>
            <ymin>301.73</ymin>
            <xmax>1506.97</xmax>
            <ymax>429.737</ymax>
        </bndbox>
    </object>
    <object>
        <name>armor</name>
        <armor_class>1</armor_class>
        <armor_color>blue</armor_color>
        <generated>0</generated>
        <is_incorrect>0</is_incorrect>
        <bndbox>
            <xmin>1177.45</xmin>
            <ymin>353.693</ymin>
            <xmax>1193.93</xmax>
            <ymax>375.239</ymax>
        </bndbox>
    </object>
    <object>
        <name>armor</name>
        <armor_class>1</armor_class>
        <armor_color>blue</armor_color>
        <generated>0</generated>
        <is_incorrect>0</is_incorrect>
        <bndbox>
            <xmin>1131.82</xmin>
            <ymin>346.089</ymin>
            <xmax>1169.85</xmax>
            <ymax>361.298</ymax>
        </bndbox>
    </object>
    <object>
        <name>armor</name>
        <armor_class>1</armor_class>
        <armor_color>blue</armor_color>
        <generated>0</generated>
        <is_incorrect>0</is_incorrect>
        <bndbox>
            <xmin>1128.02</xmin>
            <ymin>361.298</ymin>
            <xmax>1159.71</xmax>
            <ymax>379.041</ymax>
        </bndbox>
    </object>
    <object>
        <name>armor</name>
        <armor_class>2</armor_class>
        <armor_color>blue</armor_color>
        <generated>0</generated>
        <is_incorrect>0</is_incorrect>
        <bndbox>
            <xmin>1229.41</xmin>
            <ymin>431.004</ymin>
            <xmax>1254.76</xmax>
            <ymax>450.015</ymax>
        </bndbox>
    </object>
    <object>
        <name>armor</name>
        <armor_class>2</armor_class>
        <armor_color>blue</armor_color>
        <generated>0</generated>
        <is_incorrect>0</is_incorrect>
        <bndbox>
            <xmin>1183.79</xmin>
            <ymin>424.667</ymin>
            <xmax>1202.8</xmax>
            <ymax>443.678</ymax>
        </bndbox>
    </object>
    <object>
        <name>armor</name>
        <armor_class>3</armor_class>
        <armor_color>blue</armor_color>
        <generated>0</generated>
        <is_incorrect>0</is_incorrect>
        <bndbox>
            <xmin>1357.42</xmin>
            <ymin>458.887</ymin>
            <xmax>1381.5</xmax>
            <ymax>475.363</ymax>
        </bndbox>
    </object>
    <object>
        <name>armor</name>
        <armor_class>1</armor_class>
        <armor_color>red</armor_color>
        <generated>0</generated>
        <is_incorrect>0</is_incorrect>
        <bndbox>
            <xmin>978.47</xmin>
            <ymin>505.78</ymin>
            <xmax>1013.96</xmax>
            <ymax>524.791</ymax>
        </bndbox>
    </object>
    <object>
        <name>armor</name>
        <armor_class>1</armor_class>
        <armor_color>red</armor_color>
        <generated>0</generated>
        <is_incorrect>0</is_incorrect>
        <bndbox>
            <xmin>944.25</xmin>
            <ymin>481.7</ymin>
            <xmax>967.063</xmax>
            <ymax>507.048</ymax>
        </bndbox>
    </object>
    <object>
        <name>armor</name>
        <armor_class>7</armor_class>
        <armor_color>grey</armor_color>
        <generated>0</generated>
        <is_incorrect>0</is_incorrect>
        <bndbox>
            <xmin>972.133</xmin>
            <ymin>408.191</ymin>
            <xmax>1007.62</xmax>
            <ymax>424.667</ymax>
        </bndbox>
    </object>
    <object>
        <name>car</name>
        <difficulty>1</difficulty>
        <generated>0</generated>
        <is_incorrect>0</is_incorrect>
        <bndbox>
            <xmin>1171.11</xmin>
            <ymin>357.496</ymin>
            <xmax>1283.91</xmax>
            <ymax>460.154</ymax>
        </bndbox>
    </object>
    <object>
        <name>car</name>
        <difficulty>0</difficulty>
        <generated>0</generated>
        <is_incorrect>0</is_incorrect>
        <bndbox>
            <xmin>1335.87</xmin>
            <ymin>423.4</ymin>
            <xmax>1406.85</xmax>
            <ymax>488.037</ymax>
        </bndbox>
    </object>
    <object>
        <name>car</name>
        <difficulty>0</difficulty>
        <generated>0</generated>
        <is_incorrect>0</is_incorrect>
        <bndbox>
            <xmin>1109.01</xmin>
            <ymin>291.591</ymin>
            <xmax>1202.8</xmax>
            <ymax>390.448</ymax>
        </bndbox>
    </object>
    <object>
        <name>car</name>
        <difficulty>0</difficulty>
        <generated>0</generated>
        <is_incorrect>0</is_incorrect>
        <bndbox>
            <xmin>939.18</xmin>
            <ymin>438.609</ymin>
            <xmax>1029.17</xmax>
            <ymax>533.663</ymax>
        </bndbox>
    </object>
    <object>
        <name>watcher</name>
        <difficulty>0</difficulty>
        <generated>0</generated>
        <is_incorrect>0</is_incorrect>
        <bndbox>
            <xmin>956.924</xmin>
            <ymin>367.635</ymin>
            <xmax>1013.96</xmax>
            <ymax>447.48</ymax>
        </bndbox>
    </object>
</annotation>
